pjdev_postgres/__about__.py
pjdev_postgres/__init__.py
pjdev_postgres/concurrency_service.py
pjdev_postgres/model_validators.py
pjdev_postgres/models.py
pjdev_postgres/postgres_service.py
pjdev_postgres/postgres_settings.py
pjdev_postgres/py.typed
pjdev_postgres-4.6.3.dist-info/METADATA
pjdev_postgres-4.6.3.dist-info/WHEEL
pjdev_postgres-4.6.3.dist-info/licenses/LICENSE.txt
pjdev_postgres-4.6.3.dist-info/RECORD
