Metadata-Version: 2.4
Name: pjdev-postgres
Version: 4.6.3
Project-URL: Documentation, https://gitlab.purplejay.net/keystone/python/-/tree/main/keystone-postgres/README.md
Project-URL: Issues, https://gitlab.purplejay.net/keystone/python/-/issues
Project-URL: Source, https://gitlab.purplejay.net/keystone/python
Author-email: Purple Jay LLC <developers@purplejay.io>
License-Expression: MIT
License-File: LICENSE.txt
Classifier: Development Status :: 4 - Beta
Classifier: Programming Language :: Python
Classifier: Programming Language :: Python :: 3.13
Classifier: Programming Language :: Python :: Implementation :: CPython
Classifier: Programming Language :: Python :: Implementation :: PyPy
Requires-Python: >=3.13
Requires-Dist: loguru
Requires-Dist: psycopg[binary,pool]>=3.2.6
Requires-Dist: pydantic-settings>=2.8.1
Requires-Dist: sqlmodel>=0.0.24
Provides-Extra: dev
Requires-Dist: ruff; extra == 'dev'
Provides-Extra: test
Requires-Dist: coverage; extra == 'test'
Requires-Dist: pytest; extra == 'test'
Requires-Dist: pytz; extra == 'test'
